Metadata-Version: 1.0
Name: nose-cov
Version: 1.5
Summary: nose plugin for coverage reporting, including subprocesses and multiprocessing
Home-page: http://bitbucket.org/memedough/nose-cov/overview
Author: Meme Dough
Author-email: memedough@gmail.com
License: MIT License
Keywords: nose nosetest cover coverage
Platform: UNKNOWN
Classifier: Development Status :: 4 - Beta
Classifier: Intended Audience :: Developers
Classifier: License :: OSI Approved :: MIT License
Classifier: Operating System :: OS Independent
Classifier: Programming Language :: Python
Classifier: Programming Language :: Python :: 2.4
Classifier: Programming Language :: Python :: 2.5
Classifier: Programming Language :: Python :: 2.6
Classifier: Programming Language :: Python :: 2.7
Classifier: Programming Language :: Python :: 3.0
Classifier: Programming Language :: Python :: 3.1
Classifier: Topic :: Software Development :: Testing
